{"version": 4, "name": "Automated OneDest Switches", "source": "local:C75jC5ElD3ER/OneDest Switches", "presentations": [{}], "features": [{"id": "a1876105-f70c-4df7-936c-3ef6da8817fb", "data": {"x": 4061, "z": -5315, "dests": {"-90.61": ["newjersey"], "180.00": ["cityofengland", "moloka", "-,-", "spqr", "-,+"], "89.58": ["fempire", "+,+", "lyrean", "yngland", "cordoba", "aegis"]}, "radius": 10}}, {"id": "e7f21a0f-2956-4f7a-92a9-6f37707848ad", "data": {"x": 3772, "z": -5608, "dests": {"-179.64": ["-,-", "-,+", "spqr", "moloka"], "90.00": ["cityofengland"], "-89.61": ["newjersey", "cascadia"], "-0.14": ["fempire", "+,+", "lyrean", "yngland", "cordoba", "aegis"]}, "radius": 10}}, {"id": "0af60b9c-6d40-42a4-9289-ed3c55570c66", "data": {"x": 4178, "z": -5607, "dests": {"0.00": ["fempire", "+,+", "lyrean", "yngland", "cordoba", "aegis"], "-90.00": ["newjersey", "cascadia"], "179.86": ["-,-", "spqr", "moloka", "cityofengland"]}, "radius": 10}}, {"id": "c2963f0a-7cbb-4ff2-b80c-227e2122ca0e", "data": {"x": 5048, "z": -5514, "dests": {"90.00": ["yngland"], "0.12": ["fempire", "+,+", "moloka", "occident", "karydia", "lyrean", "-,+", "aegis"], "-88.36": ["cordoba"], "180.00": ["cityofengland", "-,-", "spqr", "newjersey", "baile", "stonegate", "cascadia", "deepslate"]}, "radius": 10}}, {"id": "c968cd3f-9754-47d1-9f62-9dc443ddd4a6", "data": {"x": 5048, "z": -6165, "dests": {"89.58": ["yngland"], "-90.00": ["cityofengland", "+,+", "moloka", "-,-", "spqr", "newjersey", "lyrean", "-,+", "cordoba", "aegis", "cascadia"], "0.18": ["fempire"]}, "radius": 10}}, {"id": "27b038d9-f8b1-4ccf-b5e0-f0ecbb93ad0a", "data": {"x": 5515, "z": -5515, "dests": {"45.00": ["fempire"], "-135.03": ["+,+", "moloka", "-,-", "lyrean", "-,+", "aegis"], "-179.88": ["cityofengland", "northlandia", "spqr", "newjersey", "yngland", "baile", "stonegate", "cordoba", "cascadia", "deepslate"]}, "radius": 10}}, {"id": "82504ab5-fad7-4b5f-bb20-786cd6562c87", "data": {"x": 6089, "z": -6168, "dests": {"180.00": ["fempire"], "-90.00": ["cityofengland", "+,+", "moloka", "-,-", "spqr", "newjersey", "lyrean", "-,+", "cordoba", "aegis", "cascadia"], "0.00": ["farmingrad"]}, "radius": 10}}, {"id": "008c2517-48b8-429e-a5bc-59b32ec2abad", "data": {"x": 5978, "z": -6168, "dests": {"90.00": ["fempire"], "0.00": ["cityofengland", "+,+", "moloka", "-,-", "spqr", "newjersey", "farmingrad", "lyrean", "-,+", "cordoba", "aegis", "cascadia"], "-179.82": ["yngland"]}, "radius": 10}}, {"id": "ffcc551c-017e-43ff-ab41-71e0ca60337e", "data": {"x": 1210, "z": -5650, "dests": {"-89.94": ["stonegate", "karydia", "occident", "+,+", "escobar", "lyrean", "-,+"], "89.94": ["-,-", "baile"], "-0.48": ["aegis", "impendia", "deepslate"]}, "radius": 10}}, {"id": "0f0e27d2-0ed8-4831-a9c7-bdee224c1a63", "data": {"x": -65, "z": -2668, "dests": {"-90.00": ["deluvia", "escobar", "+,+", "+,-"], "-179.91": ["karydia", "volterra", "-,+", "micronook", "icenia"], "90.00": ["northlandia", "impendia", "baile", "stonegate", "deepslate"]}, "radius": 10}}, {"id": "db3b2c64-08a3-4a3c-8692-e0445b498cce", "data": {"x": -65, "z": -2221, "dests": {"-90.24": ["escobar"], "0.00": ["deluvia", "+,+", "+,-"], "90.00": ["-,+", "northlandia", "impendia", "karydia", "occident", "baile", "stonegate", "deepslate"]}, "radius": 10}}, {"id": "30488eba-57ce-4d57-913f-e373ac4344e7", "data": {"x": 1212, "z": -7585, "dests": {"90.13": ["baile"], "180.00": ["winterbourne"], "-90.06": ["-,+", "impendia", "+,+", "-,-", "escobar", "lyrean", "stonegate", "aegis"]}, "radius": 10}}, {"id": "59690cae-82d9-4275-b517-a1d401cc807c", "data": {"x": 4434, "z": -4435, "dests": {"-134.98": ["+,+", "moloka", "-,-", "lyrean", "-,+"], "0.00": ["khalkedonia"], "44.97": ["stonegate", "cityofengland", "northlandia", "fempire", "spqr", "newjersey", "baile", "yngland", "cordoba", "cascadia"]}, "radius": 10}}, {"id": "95d635db-2c1c-4c0d-9872-db497a2a200e", "data": {"x": 3019, "z": -2613, "dests": {"-90.00": ["lambat", "margaritaville", "selene", "+,+", "moloka", "-,-", "heikki", "newmta", "-,+", "pavia", "exyria", "mehri"], "90.71": ["aegis", "impendia"], "0.00": ["develhof"]}, "radius": 10}}, {"id": "3708f870-ce6e-4b60-b2a2-42fa71a746b1", "data": {"x": 3019, "z": -2596, "dests": {"-135.31": ["lambat", "margaritaville", "selene", "+,+", "moloka", "-,-", "heikki", "newmta", "-,+", "pavia", "exyria", "mehri"], "90.00": ["aegis", "impendia"], "45.00": ["develhof"]}, "radius": 10}}, {"id": "7acb5824-0c08-4b6b-8d78-4c418d5fc008", "data": {"x": 2642, "z": -2223, "dests": {"-135.00": ["lambat", "margaritaville", "selene", "+,+", "occident", "heikki", "newmta", "deluvia", "exyria", "mehri"], "179.97": ["-,-", "-,+", "pavia", "moloka"], "44.69": ["aegis", "impendia", "develhof"]}, "radius": 10}}, {"id": "e448d27d-9573-4c20-b9fc-6c66a7fc36c1", "data": {"x": 2600, "z": -2151, "dests": {"-90.00": ["blanco", "lambat", "margaritaville", "selene", "+,+", "-,-", "thijo", "heikki", "gutch", "newmta", "deluvia", "exyria"], "0.00": ["mehri"], "90.00": ["northlandia", "impendia", "occident", "moloka", "karydia", "develhof", "-,+", "pavia", "aegis"]}, "radius": 10}}, {"id": "c82427bc-7bd5-4746-8103-dd202e7d09ce", "data": {"x": 2600, "z": -1978, "dests": {"-90.00": ["blanco", "lambat", "margaritaville", "selene", "+,+", "-,-", "thijo", "heikki", "newmta", "-,+", "exyria"], "90.00": ["northlandia", "impendia", "occident", "moloka", "mehri", "pavia", "aegis"], "180.00": ["gutch"]}, "radius": 10}}, {"id": "b5269fad-b7e4-4c5b-ae0b-9d501819b1a5", "data": {"x": 2600, "z": -1701, "dests": {"0.00": ["blanco", "lambat", "margaritaville", "selene", "+,+", "-,-", "heikki", "newmta", "-,+", "exyria"], "90.00": ["northlandia", "impendia", "occident", "moloka", "mehri", "pavia", "aegis"], "-179.15": ["thijo"]}, "radius": 10}}, {"id": "4e2411b0-d5c3-480b-a6a6-a8f7bd611e74", "data": {"x": 2817, "z": -1701, "dests": {"0.00": ["lambat", "margaritaville", "selene", "+,+", "-,-", "heikki", "newmta", "-,+", "exyria"], "180.00": ["northlandia", "impendia", "occident", "moloka", "mehri", "pavia", "aegis"], "-90.00": ["blanco"]}, "radius": 10}}, {"id": "69df11e1-a49b-4f96-8e02-fc7fe73bedc7", "data": {"x": 3050, "z": -1701, "dests": {"-90.00": ["lambat", "margaritaville", "selene", "+,+", "heikki", "newmta", "deluvia", "exyria"], "90.00": ["-,-", "-,+"], "180.00": ["northlandia", "impendia", "occident", "moloka", "mehri", "pavia", "aegis"]}, "radius": 10}}, {"id": "7b879b10-5da5-430e-aa58-e4fe7cc5bdf9", "data": {"x": 3050, "z": -1358, "dests": {"0.00": ["selene", "lambat", "exyria", "newmta"], "-90.00": ["deluvia", "heikki", "margaritaville", "+,+"], "90.00": ["impendia", "moloka", "-,-", "mehri", "-,+", "pavia", "aegis"]}, "radius": 10}}, {"id": "c33d3c7f-239c-4a6b-8afc-56628586e712", "data": {"x": 3168, "z": -1358, "dests": {"44.31": ["exyria", "newmta"], "-0.55": ["selene", "lambat"], "180.00": ["aegis", "impendia", "margaritaville", "+,+", "moloka", "-,-", "-,+", "pavia", "heikki", "mehri"]}, "radius": 10}}, {"id": "d4192ff5-0ef8-4f07-a23b-229338421aee", "data": {"x": 3878, "z": -2051, "dests": {"44.27": ["newmta"], "-41.86": ["exyria"], "-135.69": ["aegis", "lambat", "impendia", "margaritaville", "moloka", "selene", "+,+", "-,-", "-,+", "pavia", "heikki", "mehri"]}, "radius": 10}}, {"id": "2c759cd6-48f5-4b4d-8f71-6f4705ee198f", "data": {"x": 3050, "z": -833, "dests": {"180.00": ["heikki"], "-90.00": ["deluvia", "margaritaville", "+,+"], "90.00": ["aegis", "impendia", "lambat", "selene", "moloka", "-,-", "newmta", "-,+", "pavia", "exyria", "mehri"]}, "radius": 10}}, {"id": "b944a195-95e1-41be-bee0-58f526ff658b", "data": {"x": 3480, "z": -1355, "dests": {"0.00": ["lambat"], "-90.00": ["selene", "medi", "pioneer"], "179.45": ["aegis", "impendia", "margaritaville", "+,+", "moloka", "-,-", "heikki", "newmta", "-,+", "pavia", "exyria", "mehri"]}, "radius": 10}}, {"id": "46c01f94-1277-42f5-bed2-3281dcfe1279", "data": {"x": 900, "z": -2224, "dests": {"90.00": ["pavia"], "180.00": ["moloka", "-,-", "spqr", "sandtopia", "-,+"], "-0.03": ["aegis", "impendia", "lambat", "margaritaville", "selene", "+,+", "heikki", "newmta", "deluvia", "exyria", "mehri"]}, "radius": 10}}, {"id": "73dbdbfa-86bc-4149-8890-643897629a39", "data": {"x": 3050, "z": -630, "dests": {"0.00": ["margaritaville"], "-90.00": ["deluvia", "+,+"], "90.00": ["aegis", "impendia", "lambat", "selene", "moloka", "-,-", "heikki", "newmta", "-,+", "pavia", "exyria", "mehri"]}, "radius": 10}}, {"id": "930c770a-ebe3-45d9-b88b-afc0dda00be7", "data": {"x": 3887, "z": -1322, "dests": {"-14.04": ["selene", "+,+"], "90.00": ["aegis", "arctic", "impendia", "lambat", "margaritaville", "moloka", "-,-", "heikki", "newmta", "-,+", "pavia", "exyria", "mehri"], "-161.57": ["pioneer"]}, "radius": 10}}, {"id": "38464fca-d8db-4b7e-bb21-89c6cb56c46c", "data": {"x": 3891, "z": -58, "dests": {"0.00": ["selene"], "-90.00": ["+,+"], "90.00": ["aegis", "impendia", "lambat", "margaritaville", "moloka", "-,-", "heikki", "newmta", "-,+", "pavia", "exyria", "mehri"]}, "radius": 10}}, {"id": "bbb1698b-5518-46ce-8a79-d0c64d792012", "data": {"x": 3050, "z": -115, "dests": {"-90.00": ["deluvia", "+,+"], "90.00": ["aegis", "impendia", "lambat", "margaritaville", "moloka", "-,-", "heikki", "newmta", "-,+", "pavia", "exyria", "mehri"]}, "radius": 10}}, {"id": "a5fa62cc-e457-4589-b89a-01beae1717df", "data": {"x": 3050, "z": 553, "dests": {"-90.00": ["anisso", "venne", "mta", "kaiyaukuta", "skandic", "lyrean", "cigno", "papal", "ap", "nswisston", "deluvia", "medi", "snowpeak", "nara"], "0.00": ["bloxernistan"], "90.00": ["-,-", "+,-", "-,+"]}, "radius": 10}}, {"id": "002f87cf-d305-4e25-b715-5c40ce60afd2", "data": {"x": 3050, "z": 847, "dests": {"-90.00": ["anisso", "venne", "mta", "kaiyaukuta", "skandic", "ap", "papal", "nswisston", "deluvia", "medi", "cigno", "nara"], "-45.21": ["arctic", "truidencia", "santiago", "eldoria", "danzilona", "lyrean", "transylvania", "lusitania"], "90.00": ["-,-", "+,-", "bloxernistan", "-,+"]}, "radius": 10}}, {"id": "9466219f-5c68-4b96-b02e-97372fc9ef53", "data": {"x": 3050, "z": 1069, "dests": {"-0.45": ["rivia", "qbarra", "accra"], "-90.00": ["anisso", "venne", "mta", "kaiyaukuta", "skandic", "ap", "papal", "nswisston", "deluvia", "cigno", "nara"], "90.00": ["snowpeak", "-,-", "+,-", "-,+", "medi", "bloxernistan"]}, "radius": 10}}, {"id": "044410db-382d-4dee-972b-55b47671df6d", "data": {"x": 4840, "z": 1083, "dests": {"-0.47": ["rivia", "qbarra"], "90.00": ["accra"], "179.55": ["arctic", "truidencia", "santiago", "-,-", "eldoria", "danzilona", "ap", "+,-", "-,+", "transylvania", "lusitania"]}, "radius": 10}}, {"id": "8dbfb696-b020-4c43-a733-66aa07dc38bf", "data": {"x": 6650, "z": 1098, "dests": {"-1.25": ["qbarra"], "-90.00": ["rivia"], "179.53": ["arctic", "truidencia", "santiago", "-,-", "accra", "eldoria", "danzilona", "ap", "+,-", "-,+", "transylvania", "lusitania"]}, "radius": 10}}, {"id": "4e877b80-27de-4c93-8c47-e1aa34157675", "data": {"x": 3591, "z": 1392, "dests": {"-45.00": ["arctic", "truidencia", "santiago", "eldoria", "danzilona", "transylvania"], "0.19": ["+,-", "lusitania"], "134.79": ["impendia", "moloka", "-,-", "mta", "kaiyaukuta", "lyrean", "cigno", "ap", "qbarra", "-,+", "rivia", "aegis", "bloxernistan", "accra"]}, "radius": 10}}, {"id": "60bb15c6-8fa0-4d69-95b1-72fcb0e80ffe", "data": {"x": 4810, "z": 3180, "dests": {"-90.82": ["arctic", "truidencia", "karydia", "eldoria", "danzilona", "ap", "transylvania", "lusitania"], "0.00": ["santiago"], "89.70": ["-,-", "mta", "qbarra", "+,-", "-,+", "rivia", "bloxernistan", "accra"]}, "radius": 10}}, {"id": "954ca495-4500-419b-a1b8-c6762b676d75", "data": {"x": 4799, "z": 3950, "dests": {"-90.89": ["arctic", "truidencia", "karydia", "eldoria", "danzilona", "ap", "deluvia", "transylvania"], "89.18": ["santiago", "-,-", "qbarra", "+,-", "-,+", "rivia", "bloxernistan", "accra"], "0.00": ["lusitania"]}, "radius": 10}}, {"id": "33d4126f-9a4d-4857-8b81-bdbfc8adc5ab", "data": {"x": 4783, "z": 5050, "dests": {"52.88": ["danzilona"], "-90.12": ["eldoria", "transylvania", "truidencia", "arctic"], "179.94": ["anisso", "karydia", "venne", "mta", "kaiyaukuta", "skandic", "ap", "papal", "nswisston", "deluvia", "cigno", "nara"], "89.89": ["santiago", "-,-", "accra", "sophia", "qbarra", "+,-", "-,+", "rivia", "bloxernistan", "lusitania"]}, "radius": 10}}, {"id": "33472a53-2b55-48e0-995a-9f86a6c48426", "data": {"x": 4781, "z": 5978, "dests": {"0.00": ["transylvania"], "-90.17": ["eldoria", "arctic", "truidencia"], "89.88": ["santiago", "-,-", "mta", "accra", "kaiyaukuta", "danzilona", "cigno", "ap", "qbarra", "+,-", "-,+", "rivia", "bloxernistan", "lusitania"]}, "radius": 10}}, {"id": "0171456d-1ba0-4fd9-a7bb-61b67b921a8f", "data": {"x": 5340, "z": 5757, "dests": {"90.00": ["transylvania"], "-135.26": ["santiago", "-,-", "mta", "accra", "kaiyaukuta", "danzilona", "cigno", "ap", "qbarra", "+,-", "-,+", "rivia", "bloxernistan", "lusitania"], "-90.25": ["eldoria", "arctic", "truidencia"]}, "radius": 10}}, {"id": "2d7f818b-7e24-40b5-8a88-c40e76409812", "data": {"x": 3888, "z": 1391, "dests": {"-44.94": ["lusitania"], "-179.81": ["arctic", "truidencia", "impendia", "santiago", "moloka", "-,-", "eldoria", "danzilona", "lyrean", "ap", "qbarra", "-,+", "rivia", "transylvania", "aegis", "accra"], "0.00": ["+,-"]}, "radius": 10}}, {"id": "649e8d2c-9cd8-470d-87a5-f515172cb9ef", "data": {"x": 6451, "z": 3950, "dests": {"0.00": ["lusitania"], "135.00": ["-,-", "mta", "qbarra", "+,-", "-,+", "rivia", "bloxernistan", "accra"], "180.00": ["arctic", "truidencia", "karydia", "santiago", "eldoria", "danzilona", "ap", "deluvia", "transylvania"]}, "radius": 10}}, {"id": "48c29879-7b87-4630-836d-33fa12fe2f11", "data": {"x": 7920, "z": 3950, "dests": {"180.00": ["arctic", "truidencia", "santiago", "-,-", "accra", "eldoria", "danzilona", "ap", "qbarra", "+,-", "-,+", "rivia", "transylvania", "lusitania"], "90.00": ["classicale"]}, "radius": 10}}, {"id": "f8ba84c7-c1c2-434d-a146-c8339f248a8f", "data": {"x": 7770, "z": 3950, "dests": {"0.00": ["arctic", "truidencia", "santiago", "-,-", "accra", "eldoria", "danzilona", "ap", "qbarra", "+,-", "-,+", "rivia", "transylvania", "lusitania"], "-90.00": ["cascais"]}, "radius": 10}}, {"id": "ebf0a7ef-229e-47f4-a82d-e2caf12f96eb", "data": {"x": 5370, "z": 6638, "dests": {"0.09": ["eldoria", "truidencia"], "-90.00": ["papal", "nswisston", "snowpeak", "venne"], "180.00": ["arctic", "santiago", "-,-", "accra", "danzilona", "ap", "qbarra", "+,-", "-,+", "rivia", "lusitania"], "90.00": ["transylvania"]}, "radius": 10}}, {"id": "976e740c-22a4-46de-ba25-14768512740e", "data": {"x": 6000, "z": 6637, "dests": {"0.00": ["truidencia"], "90.00": ["eldoria"], "-179.91": ["arctic", "santiago", "-,-", "accra", "danzilona", "ap", "qbarra", "+,-", "-,+", "rivia", "transylvania", "lusitania"]}, "radius": 10}}, {"id": "f7142163-e5ae-49d9-8bdd-fd898103d006", "data": {"x": 3366, "z": 5050, "dests": {"0.12": ["truidencia", "venne", "santiago", "eldoria", "danzilona", "papal", "nswisston", "ichino", "transylvania", "snowpeak", "lusitania"], "90.00": ["anisso", "kaiyaukuta", "skandic", "ap", "cigno", "nara"], "180.00": ["northlandia", "founders", "occident", "karydia", "mta", "+,-", "medi", "bloxernistan"], "-90.00": ["-,-", "-,+"]}, "radius": 10}}, {"id": "c1f4cc05-be90-49b2-ba7e-7b92f4f2050a", "data": {"x": 3841, "z": 5049, "dests": {"-90.00": ["papal", "nara", "nswisston", "venne"], "-179.88": ["anisso", "-,-", "mta", "kaiyaukuta", "shiroyama", "ap", "bloxernistan", "+,-", "-,+", "medi", "cigno", "skandic"], "-0.06": ["truidencia", "santiago", "eldoria", "danzilona", "lyrean", "transylvania", "snowpeak", "lusitania"]}, "radius": 10}}, {"id": "8786d1c5-4730-4534-9bd4-b9ec557a156f", "data": {"x": 3841, "z": 7687, "dests": {"-133.56": ["papal", "nswisston", "venne"], "-90.00": ["-,-", "mta", "ap", "+,-", "-,+", "medi", "bloxernistan", "nara"], "0.04": ["eldoria", "transylvania", "truidencia", "snowpeak"]}, "radius": 10}}, {"id": "3c26cf9a-a1cf-48d2-83bc-8e9659323d26", "data": {"x": 2700, "z": 8770, "dests": {"-90.00": ["papal"], "-179.57": ["cigno", "kaiyaukuta", "nswisston", "venne"], "0.12": ["snowpeak", "-,-", "mta", "ap", "+,-", "-,+", "medi", "bloxernistan", "nara"]}, "radius": 10}}, {"id": "c4934f26-3403-4de4-aa8d-a30fd94ec77a", "data": {"x": 5365, "z": 7686, "dests": {"-90.00": ["snowpeak"], "-179.96": ["papal", "nswisston", "venne"], "0.00": ["-,-", "mta", "kaiyaukuta", "cigno", "ap", "+,-", "-,+", "medi", "bloxernistan"]}, "radius": 10}}, {"id": "2c165b99-38dc-438d-9a7c-a2bf4ec6edf0", "data": {"x": 1906, "z": 8776, "dests": {"179.85": ["anisso", "venne", "kaiyaukuta", "cigno", "skandic"], "0.43": ["snowpeak", "-,-", "mta", "ap", "papal", "+,-", "-,+", "medi", "bloxernistan", "nara"], "0.57": ["nswisston"], "180.00": ["hotel"]}, "radius": 10}}, {"id": "818dbfe0-9292-4da2-be12-0a94cba29dc4", "data": {"x": 3366, "z": 5046, "dests": {"0.00": ["anisso", "kaiyaukuta", "cigno", "skandic"], "133.83": ["aldenfult"], "-90.00": ["snowpeak", "-,-", "venne", "mta", "papal", "+,-", "-,+", "nswisston", "medi", "bloxernistan", "nara"]}, "radius": 10}}, {"id": "23cc565b-cfbc-4714-8d44-fb8a0efdcd58", "data": {"x": 1873, "z": 7466, "dests": {"-133.37": ["anisso", "venne", "kaiyaukuta", "papal", "nswisston", "skandic"], "-0.44": ["cigno"], "46.74": ["snowpeak", "-,-", "mta", "ap", "+,-", "-,+", "medi", "bloxernistan", "nara"]}, "radius": 10}}, {"id": "fdd33c12-0881-43c5-a7e5-d2859de5de1d", "data": {"x": 1582, "z": 7774, "dests": {"89.72": ["kaiyaukuta"], "46.63": ["snowpeak", "-,-", "mta", "cigno", "ap", "+,-", "-,+", "medi", "bloxernistan", "nara"], "-90.30": ["anisso", "venne", "papal", "nswisston", "skandic"]}, "radius": 10}}, {"id": "bc3d98ad-7920-43cd-bfe3-40bf136dee22", "data": {"x": 2291, "z": 4050, "dests": {"-90.00": ["aldenfult"], "-45.24": ["arctic", "-,-", "+,-", "-,+", "medi"]}, "radius": 10}}, {"id": "a00d00f0-ddb4-4a63-9c6c-b51958c582b4", "data": {"x": -1380, "z": -1335, "dests": {"180.00": ["shockton", "karydia", "-,+", "micronook", "icenia"], "0.00": ["volterra"], "90.00": ["northlandia", "+,-", "warmia"]}, "radius": 10}}, {"id": "04e4edab-8058-4243-accf-c34457e1e5d6", "data": {"x": -1690, "z": -1180, "dests": {"-90.00": ["shockton", "karydia", "-,+", "micronook", "icenia"], "90.00": ["northlandia", "+,-", "warmia"], "0.00": ["deluvia", "lyrean", "volterra", "+,+"]}, "radius": 10}}, {"id": "dac50887-5392-4f43-bb90-096ecb65c839", "data": {"x": -1690, "z": -1163, "dests": {"-90.00": ["shockton", "-,+"], "-179.86": ["deluvia", "micronook", "icenia", "karydia"], "90.00": ["northlandia", "+,+", "volterra", "+,-", "deluvia"]}, "radius": 10}}, {"id": "a5de2632-c527-45e6-8747-70d6c0ab6267", "data": {"x": -1690, "z": -1158, "dests": {"-90.00": ["-,+"], "90.00": ["northlandia", "+,+", "volterra", "+,-", "deluvia"], "0.00": ["shockton"]}, "radius": 10}}, {"id": "02555f03-b37f-4f66-9602-36c9d4b59bcf", "data": {"x": -1632, "z": -1090, "dests": {"-91.44": ["-,+"], "138.67": ["northlandia", "+,+", "volterra", "+,-"]}, "radius": 10}}, {"id": "4d17a593-aecf-41f3-8158-6218feb5592f", "data": {"x": -3994, "z": 65, "dests": {"-89.94": ["melonwood", "petergrad"], "0.00": ["-,-", "+,+", "volterra", "+,-"], "90.00": ["micronook", "icenia", "karydia"]}, "radius": 10}}, {"id": "8a2d1e0a-3a1f-442d-99c5-1ff24d3b4781", "data": {"x": -3993, "z": 958, "dests": {"-89.94": ["melonwood"], "180.00": ["petergrad"], "90.06": ["+,+", "karydia", "-,-", "+,-", "cw"]}, "radius": 10}}, {"id": "fe6c77db-0b01-40d6-b1bb-97cc763c05f7", "data": {"x": -2930, "z": -1160, "dests": {"90.00": ["micronook", "icenia"], "-136.74": ["karydia", "-,+"], "180.00": ["northlandia", "+,+", "volterra", "+,-"]}, "radius": 10}}, {"id": "5a2778e7-06e9-4369-bc4d-bf43aaf3633a", "data": {"x": -1304, "z": -1215, "dests": {"-15.95": ["volterra"], "146.31": ["northlandia", "+,-"]}, "radius": 10}}, {"id": "0add154d-aa84-46f6-b22e-11d598266d30", "data": {"x": -1270, "z": -1212, "dests": {"0.00": ["deluvia", "+,+", "volterra", "+,-"], "-172.87": ["shockton", "karydia", "-,+", "micronook", "icenia"], "180.00": ["lyrean", "northlandia", "impendia", "moloka"]}, "radius": 10}}, {"id": "0dc91e17-7e32-41d6-a858-a7cc21ca767a", "data": {"x": -4904, "z": -921, "dests": {"90.00": ["icenia", "karydia", "-,+"], "-0.03": ["northlandia", "+,+", "volterra", "+,-", "micronook"], "-89.94": ["founders"]}, "radius": 10}}, {"id": "a2d2e670-8dcf-49d3-93b3-8ac49c2b2ee2", "data": {"x": -4904, "z": -1068, "dests": {"180.00": ["karydia", "-,+"], "90.00": ["icenia"], "-90.00": ["northlandia", "founders", "+,+", "volterra", "+,-", "micronook"]}, "radius": 10}}, {"id": "4599dbee-ee2f-4b31-a241-06449bdcf9ca", "data": {"x": -5214, "z": -1068, "dests": {"90.00": ["pacem"], "180.00": ["kardovia", "carolina", "reggio", "icarus", "mercutio", "deluvia"], "0.00": ["northlandia", "+,+", "volterra", "+,-", "-,+", "micronook", "icenia"]}, "radius": 10}}, {"id": "1bfaa669-9d1c-4975-8ac6-dc5de5495a3a", "data": {"x": -7803, "z": -43, "dests": {"180.00": ["kardovia", "carolina", "+,+", "reggio", "icarus", "deluvia"], "89.88": ["northlandia", "arctic", "occident", "pacem", "mercutio", "+,-", "-,+", "medi"]}, "radius": 10}}, {"id": "cb06ca58-cd7a-448c-b90d-770f1918d832", "data": {"x": -7931, "z": -43, "dests": {"180.00": ["kardovia", "icarus"], "-106.14": ["reggio", "carolina", "deluvia", "+,+"], "0.00": ["northlandia", "arctic", "occident", "pacem", "mercutio", "+,-", "-,+", "medi"]}, "radius": 10}}, {"id": "121f9579-4cbf-4558-bb13-ebcedda15cf4", "data": {"x": -8969, "z": -120, "dests": {"90.00": ["icarus"], "0.00": ["kardovia", "carolina", "northlandia", "+,+", "occident", "reggio", "pacem", "mercutio", "+,-", "-,+"], "-89.94": ["ap", "arctic", "medi"]}, "radius": 10}}, {"id": "1cdd84c5-c5b8-4488-ab66-45a0f093107f", "data": {"x": -7722, "z": 652, "dests": {"0.00": ["reggio", "carolina"], "180.00": ["kardovia", "arctic", "founders", "-,-", "pacem", "icarus", "mercutio", "+,-", "medi"], "-89.59": ["deluvia", "+,+"]}, "radius": 10}}, {"id": "84e37759-dcac-460b-85c5-84a5e2dff1fc", "data": {"x": -6431, "z": 1407, "dests": {"-90.00": ["reggio"], "-0.12": ["carolina"], "90.00": ["kardovia", "founders", "+,+", "-,-", "pacem", "icarus", "mercutio", "+,-"], "180.00": ["ap", "arctic", "medi"]}, "radius": 10}}, {"id": "a0689f98-b865-45e8-a6a2-a48f1c05b384", "data": {"x": 790, "z": -2224, "dests": {"0.00": ["aegis", "impendia", "lambat", "margaritaville", "selene", "+,+", "newmta", "deluvia", "exyria", "pavia", "heikki", "mehri"], "-179.78": ["-,-", "-,+", "spqr", "moloka"], "90.00": ["sandtopia"]}, "radius": 10}}, {"id": "4258a1f3-3a14-446c-b6c6-37698928189f", "data": {"x": -1298, "z": -1199, "dests": {"-111.80": ["shockton", "karydia", "-,+", "micronook", "icenia"], "54.46": ["deluvia", "+,+", "volterra", "+,-"]}, "radius": 10}}, {"id": "100a4a2e-9d52-46b5-87af-f86a066ed465", "data": {"x": -1312, "z": -1180, "dests": {"180.00": ["shockton", "karydia", "-,+", "micronook", "icenia"], "45.00": ["deluvia", "+,+", "volterra", "+,-"]}, "radius": 10}}, {"id": "5f7b2cbf-d8cb-4a17-96e4-07f32d7cee11", "data": {"x": -600, "z": 5634, "dests": {"-179.89": ["karydia", "-,-", "southsea", "bay", "imperial", "east"], "-0.10": ["occident", "+,-", "+,+"], "-90.00": ["kamakura"]}, "radius": 10}}, {"id": "78324dc4-d40f-4b1d-934f-abb996b849c9", "data": {"x": -2462, "z": 5668, "dests": {"89.38": ["karydia", "-,-", "southsea", "bay", "nalora"], "0.44": ["occident", "kamakura", "+,-", "+,+"], "-90.00": ["imperial", "east"]}, "radius": 10}}, {"id": "abc9d356-a06e-4192-8ed5-dac074320c27", "data": {"x": -2888, "z": 4862, "dests": {"134.70": ["karydia", "-,-", "southsea", "bay", "imperial"], "-88.96": ["soderrike", "+,+", "priderock", "newcallisto", "feline", "godhaven", "+,-", "aethia", "east"]}, "radius": 10}}, {"id": "089f318b-ad57-4328-b177-d23cc9fa7386", "data": {"x": -3890, "z": 4382, "dests": {"-179.63": ["groveheart", "karydia", "-,-", "southsea", "brunsvik", "vermont"], "0.46": ["+,+", "priderock", "newcallisto", "freeport", "feline", "godhaven", "+,-", "aethia", "east"], "-90.00": ["bay", "imperial"]}, "radius": 10}}, {"id": "ca5118f4-5331-4849-9f89-6ed1e4ed86d5", "data": {"x": -5287, "z": 4703, "dests": {"180.00": ["karydia", "moloka", "-,-", "bay", "lyrean"], "0.15": ["+,+", "freeport", "+,-", "imperial", "east"], "90.00": ["southsea"]}, "radius": 10}}, {"id": "8465ee93-df59-4e97-847d-824c68a433ca", "data": {"x": -6339, "z": 4703, "dests": {"119.74": ["-,-", "bay", "+,-", "karydia"], "0.00": ["impendia", "+,+", "southsea", "lyrean", "imperial", "east"], "-52.45": ["vallstena", "soderrike", "regensburg"]}, "radius": 10}}, {"id": "50400b2e-f6de-4cdc-8577-73f5052b5e11", "data": {"x": -6483, "z": 4451, "dests": {"134.87": ["-,-", "+,-", "karydia"], "-60.26": ["soderrike", "impendia", "+,+", "priderock", "southsea", "newcallisto", "regensburg", "vallstena", "lyrean", "feline", "godhaven", "aethia", "east"], "-129.95": ["bay", "imperial"]}, "radius": 10}}, {"id": "253d01ab-84d8-4ead-b605-ab529f270eb0", "data": {"x": -8622, "z": 1732, "dests": {"179.83": ["kardovia", "icarus"], "71.57": ["carolina", "reggio", "-,-", "mercutio", "+,-"], "-89.90": ["deluvia", "+,+"]}, "radius": 10}}, {"id": "52604921-b96c-42f6-8ea0-6471286cc370", "data": {"x": -7995, "z": 1402, "dests": {"-90.00": ["reggio", "carolina"], "49.40": ["-,-", "mercutio", "+,-"], "-175.52": ["deluvia", "+,+"]}, "radius": 10}}, {"id": "570a5178-c731-4861-bd47-08ad485b2d9a", "data": {"x": 735, "z": 8900, "dests": {"-90.00": ["anisso", "kaiyaukuta", "cigno", "skandic"], "90.00": ["-,+", "snowpeak", "-,-", "mta", "ap", "papal", "+,-", "nswisston", "medi", "bloxernistan"]}, "radius": 10}}, {"id": "ba543195-9b8e-4e7b-a921-870b63e6ede7", "data": {"x": 735, "z": 8994, "dests": {"-90.00": ["anisso", "kaiyaukuta", "cigno", "skandic"], "90.00": ["papal", "nswisston", "venne"]}, "radius": 10}}, {"id": "13dadab4-396a-4838-9ce1-5480f6aa9c01", "data": {"x": 1272, "z": 9372, "dests": {"45.47": ["-,+", "rozzano", "-,-", "kaiyaukuta", "inverastore", "corino", "lavenzia", "+,-", "ardenmara", "medi", "cigno", "nara"], "-89.73": ["skandic", "papal", "nswisston", "venne"], "180.00": ["anisso", "sasso"]}, "radius": 10}}, {"id": "3950cf2c-19af-4098-a85c-4004be3bb8d9", "data": {"x": 1575, "z": 9064, "dests": {"-90.23": ["-,+", "rozzano", "-,-", "kaiyaukuta", "inverastore", "corino", "lavenzia", "+,-", "medi", "cigno", "nara"], "-134.53": ["montevetta", "venne", "papal", "ardroch", "nswisston", "skandic"], "180.00": ["anisso"]}, "radius": 10}}, {"id": "43b76529-140e-4b05-9963-599f59668489", "data": {"x": 1574, "z": 9318, "dests": {"89.70": ["-,-", "kaiyaukuta", "+,-", "-,+", "medi", "cigno", "nara"], "89.77": ["anisso", "venne", "papal", "nswisston", "skandic"], "0.00": ["inverastore", "corino", "lavenzia"]}, "radius": 10}}, {"id": "85178950-f7a0-4883-afb7-1366b59c62d5", "data": {"x": -3590, "z": 1990, "dests": {"179.57": ["+,+", "karydia", "-,-", "+,-", "petergrad", "cw"]}, "radius": 10}}, {"id": "2b209360-58cc-452c-8e3b-b4bb9217e052", "data": {"x": 3036, "z": -2613, "dests": {"45.00": ["mehri"], "180.00": ["impendia"], "-135.00": ["blanco", "lambat", "+,+", "moloka", "-,-", "thijo", "gutch", "-,+", "pavia"]}, "radius": 10}}, {"id": "9d327611-436a-43ca-8b57-7f38f6ddf794", "data": {"x": 2465, "z": -1699, "dests": {"179.74": ["mehri"], "0.85": ["blanco", "impendia", "lambat", "+,+", "moloka", "-,-", "develhof", "gutch", "-,+", "pavia"]}, "radius": 10}}, {"id": "3b38c66c-c908-478d-8e22-c669f2fa9cdc", "data": {"x": 1823, "z": 9442, "dests": {"0.00": ["anisso"], "90.46": ["-,+", "rozzano", "montevetta", "-,-", "nswisston", "+,-", "ardenmara", "ardroch", "medi", "nara", "skandic"]}, "radius": 10}}, {"id": "e1419e4d-386e-430b-a58e-47614f5a75fb", "data": {"x": 1876, "z": 9479, "dests": {"-51.81": ["anisso"], "0.00": ["inverastore"], "-89.68": ["-,+", "rozzano", "montevetta", "-,-", "nswisston", "+,-", "ardenmara", "ardroch", "medi", "nara", "skandic"]}, "radius": 10}}, {"id": "6658244c-2f22-4b5e-aed1-a3dc64b3d20b", "data": {"x": 2016, "z": 9657, "dests": {"-90.00": ["anisso"], "0.19": ["corino"], "128.19": ["-,+", "rozzano", "montevetta", "-,-", "inverastore", "nswisston", "+,-", "ardenmara", "ardroch", "medi", "nara", "skandic"]}, "radius": 10}}, {"id": "2dd07526-9d77-4df3-9079-55b3b8b24801", "data": {"x": 1078, "z": 9372, "dests": {"90.00": ["anisso"], "-179.33": ["ardroch", "skandic"], "0.00": ["-,+", "rozzano", "-,-", "inverastore", "corino", "nswisston", "+,-", "ardenmara", "lavenzia", "skandiccity", "medi", "nara"]}, "radius": 10}}, {"id": "a98ff353-383e-475d-b35b-fe9fdff00998", "data": {"x": 865, "z": 9517, "dests": {"87.32": ["anisso"], "180.00": ["skandic"], "0.00": ["-,+", "rozzano", "montevetta", "-,-", "inverastore", "corino", "nswisston", "+,-", "ardenmara", "lavenzia", "skandiccity", "medi", "nara"]}, "radius": 10}}, {"id": "a1c9dee4-9035-4da8-a887-1bf5b8f0eefb", "data": {"x": 752, "z": 9517, "dests": {"-90.19": ["skandic"], "0.00": ["anisso", "-,+", "-,-", "nswisston", "+,-", "skandiccity", "medi", "nara"]}, "radius": 10}}, {"id": "4a08b615-2c37-42a6-b60c-18252b409e9e", "data": {"x": -2458, "z": 6356, "dests": {"-89.95": ["oldsurmadri", "voldi", "imperial", "vermont", "east"], "90.82": ["alx"], "180.00": ["kamakura", "+,+", "-,-", "southsea", "bay", "+,-"]}, "radius": 10}}, {"id": "17ee8f46-43d0-4b5b-985f-6c5c8ec21628", "data": {"x": -2457, "z": 7553, "dests": {"-90.00": ["imperial", "vermont", "oldsurmadri", "voldi"], "0.00": ["east"], "90.05": ["alx", "kamakura", "+,+", "-,-", "southsea", "bay", "+,-"]}, "radius": 10}}, {"id": "6a015eb5-f4a0-4554-8aa4-3cb6b24b6984", "data": {"x": -2728, "z": 7835, "dests": {"180.00": ["oldsurmadri", "vallstena", "voldi", "imperial", "vermont"], "-90.00": ["feline"], "0.00": ["+,+", "-,-", "southsea", "bay", "+,-", "east"]}, "radius": 10}}, {"id": "eaa36564-8546-44c1-b4bb-ebb3d53fd99f", "data": {"x": -2850, "z": 8039, "dests": {"-178.15": ["imperial"], "0.00": ["soderrike", "priderock", "regensburg", "bay", "godhaven", "nalora"], "91.09": ["+,+", "-,-", "southsea", "brunsvik", "feline", "+,-", "east"]}, "radius": 10}}, {"id": "ff6efa24-e4ea-4584-98a9-1014775e7db1", "data": {"x": -2317, "z": 8476, "dests": {"-50.44": ["imperial"], "-140.91": ["bay", "soderrike", "nalora", "regensburg"], "135.20": ["+,+", "-,-", "southsea", "newcallisto", "feline", "+,-", "aethia", "east"], "42.90": ["esberg"]}, "radius": 10}}, {"id": "a15fe930-66a2-413f-833e-70c49934ac08", "data": {"x": -3256, "z": 8029, "dests": {"-174.40": ["imperial"], "-0.73": ["soderrike", "+,+", "priderock", "-,-", "southsea", "regensburg", "bay", "feline", "godhaven", "+,-", "aethia", "east", "nalora"]}, "radius": 10}}, {"id": "93863854-0b9c-4f7f-a0ed-d5e27d8bc1fb", "data": {"x": -2814, "z": 8924, "dests": {"-82.45": ["imperial"], "-179.75": ["grenada", "-,-", "regensburg", "bay", "nalora"], "45.53": ["+,+", "priderock", "occident", "southsea", "newcallisto", "feline", "godhaven", "+,-", "aethia", "east"]}, "radius": 10}}, {"id": "615c7f1a-3c5e-4efe-9660-95ff8140e901", "data": {"x": -3890, "z": 6008, "dests": {"-90.00": ["bay", "imperial", "esberg"], "-179.83": ["vallstena", "-,-"], "90.00": ["southsea", "east", "+,+", "+,-"]}, "radius": 10}}, {"id": "e065e9e1-0eda-4c13-9ded-d9f1c3e49952", "data": {"x": -3426, "z": 7112, "dests": {"-89.87": ["bay", "imperial", "esberg"], "180.00": ["+,+", "-,-", "southsea", "vallstena", "+,-", "east"]}, "radius": 10}}, {"id": "989ace2b-6fd5-4891-911c-865908a486c0", "data": {"x": -3425, "z": 7553, "dests": {"180.00": ["bay", "imperial"], "90.13": ["kamakura", "+,+", "-,-", "southsea", "vallstena", "+,-"], "-90.00": ["soderrike", "priderock", "newcallisto", "regensburg", "feline", "godhaven", "aethia", "east"]}, "radius": 10}}, {"id": "dd8c9d59-822a-4b6b-bf17-906833b59939", "data": {"x": -3591, "z": 7553, "dests": {"-90.00": ["imperial"], "-179.86": ["bay", "-,-", "moloka"], "0.00": ["soderrike", "+,+", "priderock", "southsea", "newcallisto", "regensburg", "vallstena", "feline", "godhaven", "+,-", "aethia", "east"]}, "radius": 10}}, {"id": "bf234242-14d4-4aca-a376-d76e292695d2", "data": {"x": -3512, "z": 8927, "dests": {"91.30": ["bay", "imperial", "southsea", "-,-"], "0.25": ["soderrike", "+,+", "priderock", "newcallisto", "feline", "godhaven", "+,-", "aethia", "east"]}, "radius": 10}}, {"id": "46404813-d5d7-4670-88e9-37db22c3ee90", "data": {"x": -2430, "z": 7553, "dests": {"99.46": ["east"], "0.00": ["esberg"], "180.00": ["alx", "kamakura", "+,+", "-,-", "southsea", "bay", "+,-", "imperial"]}, "radius": 10}}, {"id": "404cf23c-a085-4f85-a68b-d96ca349db3f", "data": {"x": -1950, "z": 7553, "dests": {"90.00": ["east"], "180.00": ["alx", "groveheart", "kamakura", "+,+", "-,-", "ostersund", "southsea", "brunsvik", "+,-", "imperial"], "-90.00": ["soderrike", "priderock", "regensburg", "bay", "godhaven", "nalora"]}, "radius": 10}}, {"id": "45a89aca-a706-406b-a9a6-9e03b8e46a8c", "data": {"x": -600, "z": 6387, "dests": {"-90.00": ["east"], "90.00": ["alx", "+,+", "-,-", "ostersund", "southsea", "esberg", "bay", "+,-", "imperial"]}, "radius": 10}}, {"id": "2fed6170-6772-4947-b6e2-c2dc62229adc", "data": {"x": -600, "z": 6703, "dests": {"180.00": ["east"], "90.00": ["alx", "+,+", "-,-", "ostersund", "southsea", "esberg", "bay", "+,-", "imperial"]}, "radius": 10}}, {"id": "ba5f9de0-21af-48be-8c36-4eb012c00868", "data": {"x": -4923, "z": 7553, "dests": {"90.00": ["bay"], "180.00": ["groveheart", "grenada", "-,-", "brunsvik", "voldi", "+,-", "vermont"], "0.09": ["impendia", "+,+", "southsea", "vallstena", "lyrean", "imperial", "east"]}, "radius": 10}}, {"id": "e0ae58f3-e0ab-4a08-8e32-30c216478a08", "data": {"x": -4923, "z": 6011, "dests": {"-89.98": ["bay"], "-90.00": ["groveheart", "grenada", "moloka", "-,-", "brunsvik", "vermont"], "0.17": ["oldsurmadri", "+,+", "southsea", "voldi", "+,-", "imperial", "east"]}, "radius": 10}}, {"id": "5487d19b-1729-42b7-aa65-b2e323aa200e", "data": {"x": -6787, "z": 4814, "dests": {"-90.00": ["bay", "imperial"], "149.04": ["brunsvik"], "50.05": ["+,+", "-,-", "southsea", "newcallisto", "vallstena", "feline", "+,-", "aethia", "east"]}, "radius": 10}}, {"id": "9f45a9d6-4afb-42f3-90bd-e8fabf7d408e", "data": {"x": -6787, "z": 5580, "dests": {"-90.00": ["bay", "imperial"], "90.00": ["+,+", "-,-", "southsea", "brunsvik", "feline", "+,-", "east"], "0.00": ["vallstena"]}, "radius": 10}}, {"id": "22f98355-16de-4e12-8386-0b11630ed174", "data": {"x": -6349, "z": 7553, "dests": {"90.00": ["bay"], "0.00": ["east", "imperial", "oldsurmadri", "voldi"], "180.00": ["groveheart", "kamakura", "+,+", "-,-", "southsea", "brunsvik", "vallstena", "+,-"]}, "radius": 10}}, {"id": "a433f7f0-c6d1-4229-9f28-76a2fa22079e", "data": {"x": -5441, "z": 7553, "dests": {"-90.00": ["bay"], "0.00": ["impendia", "oldsurmadri", "+,+", "vallstena", "lyrean", "freeport", "imperial", "east"], "180.00": ["groveheart", "-,-", "southsea", "brunsvik", "+,-", "vermont"]}, "radius": 10}}, {"id": "1108ee36-30a1-4e51-b142-6b8111260066", "data": {"x": -4923, "z": 6545, "dests": {"90.00": ["bay", "imperial"], "127.55": ["-,-", "southsea", "brunsvik", "+,-"], "180.00": ["groveheart", "vermont"]}, "radius": 10}}, {"id": "5b2e462b-0995-4ffe-b462-c5996416f5ae", "data": {"x": -3523, "z": 8802, "dests": {"90.65": ["bay", "imperial", "southsea", "-,-"], "-88.45": ["soderrike", "priderock", "newcallisto", "regensburg", "feline", "godhaven", "aethia", "east"]}, "radius": 10}}, {"id": "2236a010-48b7-454c-a524-3923a464467c", "data": {"x": -5914, "z": 5580, "dests": {"180.00": ["bay"], "-90.00": ["vallstena"]}, "radius": 10}}]}