{"version": 4, "name": "Automated OneDest Switches", "source": "local:C75jC5ElD3ER/OneDest Switches", "presentations": [{}], "features": [{"id": "6058cc83-c3ee-4a07-93a9-9fc544280710", "data": {"x": 4061, "z": -5315, "dests": ["cascadia", "spqr", "cityofengland", "newjersey", "impendia"], "radius": 10}}, {"id": "5799e7dd-b3d1-4417-9092-c1284045eaa7", "data": {"x": 4178, "z": -5607, "dests": ["cascadia", "spqr", "cityofengland", "fempire", "impendia", "yngland"], "radius": 10}}, {"id": "e98c2c14-7196-4eae-a4c5-fb106e1d3679", "data": {"x": 5048, "z": -5514, "dests": ["cordoba", "escobar", "cascadia", "spqr", "cityofengland", "fempire", "impendia", "moloka", "yngland", "deepslate"], "radius": 10}}, {"id": "73657d89-dc28-40a5-bf2a-b6e005f6fb61", "data": {"x": 5515, "z": -5515, "dests": ["cordoba", "escobar", "cascadia", "spqr", "cityofengland", "fempire", "impendia", "moloka", "yngland", "deepslate"], "radius": 10}}, {"id": "d11b4957-8f7f-4637-a065-dc16fd5a658b", "data": {"x": 4434, "z": -4435, "dests": ["escobar", "aegis", "cascadia", "spqr", "cityofengland", "+,+", "medi", "impendia", "moloka", "yngland", "deepslate"], "radius": 10}}, {"id": "7b1b18e9-3ff8-4ef4-a9ae-f4642df45f7b", "data": {"x": 3019, "z": -2613, "dests": ["escobar", "aegis", "cascadia", "spqr", "cityofengland", "+,+", "medi", "impendia", "moloka", "yngland", "deepslate"], "radius": 10}}, {"id": "3ca1b11e-7137-43b8-99e6-98236e167d63", "data": {"x": 3019, "z": -2596, "dests": ["escobar", "aegis", "cascadia", "spqr", "cityofengland", "+,+", "medi", "lyrean", "impendia", "moloka", "yngland", "deepslate", "mehri"], "radius": 10}}, {"id": "ce9b2893-0420-400f-95db-0443a71b5ca4", "data": {"x": 2642, "z": -2223, "dests": ["pavia", "escobar", "aegis", "cascadia", "spqr", "-,-", "cityofengland", "+,+", "medi", "lyrean", "impendia", "moloka", "yngland", "deepslate", "mehri"], "radius": 10}}, {"id": "26c71453-673a-4f0a-9fd3-09fe1e0818b4", "data": {"x": 900, "z": -2224, "dests": ["pavia", "escobar", "aegis", "cascadia", "spqr", "-,-", "cityofengland", "+,+", "lyrean", "impendia", "moloka", "yngland", "deepslate", "mehri"], "radius": 10}}, {"id": "ab38711f-50e5-4eb9-b643-0faf96da7f45", "data": {"x": 790, "z": -2224, "dests": ["pavia", "escobar", "aegis", "cascadia", "spqr", "-,-", "cityofengland", "+,+", "lyrean", "impendia", "moloka", "yngland", "deepslate", "mehri"], "radius": 10}}, {"id": "3654ba66-8c08-41f7-9735-a610fffe8c22", "data": {"x": -65, "z": -2221, "dests": ["+,-", "lyrean", "impendia", "moloka", "occident"], "radius": 10}}, {"id": "4e4c4b28-723b-43c2-a62b-377e56e8df20", "data": {"x": -65, "z": -2668, "dests": ["+,-", "lyrean", "impendia", "moloka", "occident"], "radius": 10}}, {"id": "57c9f08c-4968-438d-bd07-865e3b68a77c", "data": {"x": 1210, "z": -5650, "dests": ["escobar", "stonegate", "cascadia", "spqr", "baile", "cityofengland", "lyrean", "impendia", "moloka", "yngland", "deepslate", "mehri"], "radius": 10}}, {"id": "ff0bb03c-dc3f-417f-8378-4295d081690d", "data": {"x": 3772, "z": -5608, "dests": ["cascadia", "cityofengland", "fempire", "impendia", "yngland"], "radius": 10}}, {"id": "29303203-9284-4593-aa30-888ba9fbe537", "data": {"x": 5048, "z": -6165, "dests": ["cordoba", "cascadia", "fempire", "impendia", "yngland"], "radius": 10}}, {"id": "6b405e7d-9c58-4842-a007-05678df5959b", "data": {"x": 6089, "z": -6168, "dests": ["cordoba", "cascadia", "fempire", "impendia", "moloka"], "radius": 10}}, {"id": "2d1079b2-0937-4c57-b3a5-ad09fd276ad5", "data": {"x": 2600, "z": -2151, "dests": ["pavia", "-,-", "+,+", "medi", "lyrean", "impendia", "mehri"], "radius": 10}}, {"id": "44152838-e01d-4c7b-9479-16111d33beb5", "data": {"x": 3036, "z": -2613, "dests": ["lyrean", "impendia", "mehri"], "radius": 10}}, {"id": "ef212124-4129-4848-b1d8-ecc77aceb60c", "data": {"x": 2600, "z": -1701, "dests": ["pavia", "lambat", "-,-", "+,+", "medi", "lyrean", "impendia", "mehri"], "radius": 10}}, {"id": "36934c86-e03f-46b5-ad25-18a920b68cbc", "data": {"x": 2465, "z": -1699, "dests": ["lyrean", "lambat", "impendia", "mehri"], "radius": 10}}, {"id": "3d13455f-c3ab-4d17-b19a-3d94c8ec601d", "data": {"x": 3050, "z": -1701, "dests": ["pavia", "lambat", "-,-", "+,+", "medi", "lyrean", "impendia"], "radius": 10}}, {"id": "1117366c-d9ec-4097-932d-2a86894fde4a", "data": {"x": 3050, "z": -1358, "dests": ["pavia", "lambat", "-,-", "+,+", "medi", "lyrean", "impendia"], "radius": 10}}, {"id": "adee233b-b64f-457d-b8ee-4d494925f09a", "data": {"x": 3480, "z": -1355, "dests": ["lyrean", "lambat", "pavia", "impendia"], "radius": 10}}, {"id": "1d054f9e-9a39-4f61-9f7e-98e4ffea8105", "data": {"x": 3887, "z": -1322, "dests": ["lyrean", "lambat", "impendia"], "radius": 10}}, {"id": "f1ec2b7c-e629-414d-990a-87af15b82452", "data": {"x": 3050, "z": 0, "dests": ["-,-", "+,-", "medi", "danzilona", "qbarra"], "radius": 10}}, {"id": "f083bd64-7063-4798-8b2b-cc0e70ca02be", "data": {"x": 3050, "z": 847, "dests": ["accra", "rivia", "medi", "+,-", "danzilona", "qbarra"], "radius": 10}}, {"id": "f234bf46-3b1e-4b25-8579-c5ea9ff56287", "data": {"x": 3050, "z": 1069, "dests": ["accra", "rivia", "+,-", "medi", "danzilona", "arctic", "papal", "mta", "qbarra"], "radius": 10}}, {"id": "86ebfbdd-2a17-40cb-8496-3feadb84db4a", "data": {"x": 4840, "z": 1083, "dests": ["accra", "rivia", "+,-", "medi", "danzilona", "arctic", "papal", "mta", "qbarra"], "radius": 10}}, {"id": "4e56e25d-2e0f-4f04-818d-3c0f2cdbc851", "data": {"x": 6650, "z": 1098, "dests": ["accra", "rivia", "medi", "+,-", "danzilona", "arctic", "qbarra"], "radius": 10}}, {"id": "580ca7ed-b1b5-4582-a8f2-580e80434736", "data": {"x": 4810, "z": 3180, "dests": ["notdoneyet", "accra", "rivia", "medi", "+,-", "danzilona"], "radius": 10}}, {"id": "7b775b83-da15-411b-a0ed-610b0d842176", "data": {"x": 4799, "z": 3950, "dests": ["notdoneyet", "lusitania", "eldoria", "truidencia", "medi", "+,-", "danzilona", "rivia"], "radius": 10}}, {"id": "f4883dfa-857b-42de-8c2e-1d6ee9175f1d", "data": {"x": 4783, "z": 5050, "dests": ["transylvania", "notdoneyet", "lusitania", "eldoria", "truidencia", "medi", "+,-", "danzilona", "arctic", "rivia", "snowpeak"], "radius": 10}}, {"id": "705e3cca-e5e1-4d8b-9c64-ccfa606d84c5", "data": {"x": 4781, "z": 5978, "dests": ["transylvania", "notdoneyet", "lusitania", "eldoria", "truidencia", "medi", "+,-", "rivia", "arctic", "snowpeak"], "radius": 10}}, {"id": "3ec94e8f-50c9-41eb-aeea-7b55add3f277", "data": {"x": 5340, "z": 5757, "dests": ["lusitania", "transylvania", "medi", "+,-"], "radius": 10}}, {"id": "c137f3e3-1c70-4b0d-8baf-ca10aefe883c", "data": {"x": 6451, "z": 3950, "dests": ["lusitania", "eldoria", "truidencia", "medi", "+,-"], "radius": 10}}, {"id": "3cf65b82-83e3-4a04-8c1d-9cf0a2e6281d", "data": {"x": 7770, "z": 3950, "dests": ["lusitania", "eldoria", "truidencia", "medi", "+,-"], "radius": 10}}, {"id": "cc432d15-3f1b-4bf1-b833-e7506c05e876", "data": {"x": 5370, "z": 6638, "dests": ["notdoneyet", "eldoria", "truidencia", "+,-", "medi", "rivia", "arctic", "snowpeak"], "radius": 10}}, {"id": "e9fc0da3-33f0-4e73-b404-2b719116fabb", "data": {"x": 6000, "z": 6637, "dests": ["notdoneyet", "eldoria", "truidencia", "medi", "+,-", "rivia"], "radius": 10}}, {"id": "b4b0bac2-c6cc-4154-945a-ad043004f77b", "data": {"x": 3050, "z": 2210, "dests": ["nara", "-,-", "+,-", "papal", "arctic", "mta"], "radius": 10}}, {"id": "7f8da4ac-acf6-4b9f-a7b7-7da56a3bdb4c", "data": {"x": 3366, "z": 5050, "dests": ["ap", "nara", "skandic", "-,-", "kaiyaukuta", "+,-", "snowpeak", "anisso", "arctic", "papal", "mta"], "radius": 10}}, {"id": "a0efefe8-a0a7-468f-bd7d-f80111c4b18b", "data": {"x": 3841, "z": 5049, "dests": ["ap", "nara", "skandic", "-,-", "kaiyaukuta", "nswisston", "snowpeak", "+,-", "anisso", "arctic", "papal", "mta"], "radius": 10}}, {"id": "99dfb5e7-cd8b-4bc1-912b-28161a2b3fb2", "data": {"x": 3841, "z": 7687, "dests": ["ap", "skandic", "nara", "-,-", "kaiyaukuta", "nswisston", "+,-", "anisso", "arctic", "papal", "mta"], "radius": 10}}, {"id": "2606ef41-3808-4309-bca6-37f123bef75f", "data": {"x": 2700, "z": 8770, "dests": ["ap", "skandic", "nara", "-,-", "kaiyaukuta", "nswisston", "+,-", "anisso", "arctic", "papal", "mta"], "radius": 10}}, {"id": "96e3aa28-a640-44fe-854e-399118e1889c", "data": {"x": 3366, "z": 5046, "dests": ["ap", "nara", "skandic", "-,-", "kaiyaukuta", "+,-", "snowpeak", "anisso", "arctic"], "radius": 10}}, {"id": "da9e92ea-53de-4508-bc0e-6b3270d29ba5", "data": {"x": 5365, "z": 7686, "dests": ["nswisston", "snowpeak", "+,-", "arctic"], "radius": 10}}, {"id": "e042f449-37e4-45e9-8350-0135cd98ac11", "data": {"x": 1906, "z": 8776, "dests": ["ap", "skandic", "-,-", "venne", "nswisston", "kaiyaukuta", "+,-", "anisso", "arctic"], "radius": 10}}, {"id": "41bcac4f-324a-4b6a-b3d7-d8a584150eb2", "data": {"x": 735, "z": 8900, "dests": ["ap", "skandic", "-,-", "venne", "kaiyaukuta", "+,-", "anisso", "arctic"], "radius": 10}}, {"id": "83797621-0dac-4a36-bdc7-f0b7fd4e163e", "data": {"x": 1873, "z": 7466, "dests": ["ap", "skandic", "cigno", "kaiyaukuta", "+,-", "anisso", "arctic"], "radius": 10}}, {"id": "e5f65276-e31e-4ed9-a46b-d6492367be17", "data": {"x": 1582, "z": 7774, "dests": ["skandic", "cigno", "kaiyaukuta", "+,-", "anisso", "arctic"], "radius": 10}}, {"id": "216b88a4-0f93-4bce-adf8-54fe5911b36b", "data": {"x": 2291, "z": 4050, "dests": ["ap", "+,-", "-,-"], "radius": 10}}, {"id": "e996bd3b-150a-453b-acff-b990dedbd304", "data": {"x": 5978, "z": -6315, "dests": ["fempire"], "radius": 10}}, {"id": "8f547a21-4f06-4b34-b37a-21c9a02cad2d", "data": {"x": -4904, "z": -1068, "dests": ["-,+", "occident"], "radius": 10}}, {"id": "efea7d52-cfe2-43e2-8da4-a781439ed806", "data": {"x": -2317, "z": 8476, "dests": ["imperial"], "radius": 10}}, {"id": "206a1e02-19d8-4204-841e-3e442bed5ddd", "data": {"x": -3256, "z": 8029, "dests": ["imperial"], "radius": 10}}, {"id": "13683535-315f-431d-bfa4-9cb5b8e1050a", "data": {"x": -3512, "z": 8927, "dests": ["imperial", "bay"], "radius": 10}}, {"id": "be04425f-f7ba-4ba9-a520-9a651269f6f2", "data": {"x": -3523, "z": 8802, "dests": ["imperial", "bay"], "radius": 10}}, {"id": "ae413cb0-17a8-4358-adf7-3ce116ce5125", "data": {"x": -3425, "z": 7553, "dests": ["imperial", "bay"], "radius": 10}}, {"id": "a5bacfeb-6774-43ff-b41b-d3d1301f3c93", "data": {"x": -3591, "z": 7553, "dests": ["imperial", "bay"], "radius": 10}}, {"id": "b4265d50-953a-41d8-91c1-cf3fdfc33ba6", "data": {"x": -4923, "z": 7553, "dests": ["bay", "imperial"], "radius": 10}}, {"id": "cac13f5b-d146-4bc2-b872-d918575af020", "data": {"x": -6349, "z": 7553, "dests": ["bay", "imperial"], "radius": 10}}, {"id": "4994522d-945b-4650-af30-5f2d67a5fed6", "data": {"x": -2430, "z": 7553, "dests": ["east", "deluvia", "bay"], "radius": 10}}, {"id": "557fd607-d22f-4a9a-a2b0-67757d3a8a00", "data": {"x": -2457, "z": 7553, "dests": ["east", "deluvia", "bay"], "radius": 10}}, {"id": "cb75d5e7-17a9-4d25-8ee4-163f4acf118e", "data": {"x": -2458, "z": 6356, "dests": ["east", "deluvia", "bay"], "radius": 10}}, {"id": "6c29b9fd-e0ea-483e-be9b-54010e366a46", "data": {"x": -2462, "z": 5668, "dests": ["bay", "deluvia", "east"], "radius": 10}}, {"id": "0910d709-fe2b-44e4-9282-013006445371", "data": {"x": -2888, "z": 4862, "dests": ["bay", "deluvia", "east"], "radius": 10}}, {"id": "886dc624-992c-4031-bee7-21e3c395bdc1", "data": {"x": -3890, "z": 4382, "dests": ["southsea", "-,-", "bay", "east", "deluvia"], "radius": 10}}, {"id": "d4405363-24a4-442c-9d04-0ac619b9c8fa", "data": {"x": -5287, "z": 4703, "dests": ["southsea", "-,-", "bay", "east", "karydia", "deluvia"], "radius": 10}}, {"id": "50220a35-82b8-4258-9327-24755bb5d0eb", "data": {"x": -6339, "z": 4703, "dests": ["southsea", "-,-", "bay", "east", "karydia", "deluvia"], "radius": 10}}, {"id": "af0dfaca-7c53-4fc4-b944-7e1ab25ae1df", "data": {"x": -4923, "z": 6545, "dests": ["bay", "deluvia", "east", "southsea"], "radius": 10}}, {"id": "14a36244-657d-4244-bc9d-f3cb8e3d94ce", "data": {"x": -6483, "z": 4451, "dests": ["southsea", "-,-", "bay", "east", "karydia", "deluvia"], "radius": 10}}, {"id": "8ea15ca4-3543-4271-9d7e-06ce9045afbc", "data": {"x": -8622, "z": 1732, "dests": ["deluvia", "karydia", "-,-"], "radius": 10}}, {"id": "5e5f0508-ff8a-4ddd-b655-257ebeb60b15", "data": {"x": -7995, "z": 1402, "dests": ["deluvia", "karydia", "-,-"], "radius": 10}}, {"id": "a4a99d0d-e4af-4bbf-8138-ba5c9c7302a1", "data": {"x": -7722, "z": 652, "dests": ["deluvia", "karydia", "-,-"], "radius": 10}}, {"id": "128e938b-7716-49fd-853a-3b4c7ec5b846", "data": {"x": -7931, "z": -43, "dests": ["mercutio", "pacem", "-,+", "karydia", "icarus", "kaowta"], "radius": 10}}, {"id": "8b468be1-9525-40f6-832a-783dfa388dc3", "data": {"x": -5214, "z": -1068, "dests": ["mercutio", "pacem", "-,+", "karydia", "icarus", "kaowta"], "radius": 10}}, {"id": "e9d020f1-2f76-4be7-9436-7fa7a0547169", "data": {"x": -7934, "z": -50, "dests": ["karydia", "icarus", "kaowta"], "radius": 10}}, {"id": "810ebecb-1d9b-487c-8b44-639679d290dc", "data": {"x": -8969, "z": -120, "dests": ["karydia", "icarus", "kaowta", "-,+"], "radius": 10}}, {"id": "69c68bb1-a516-4551-bed8-cbf049a4d842", "data": {"x": -6431, "z": 1408, "dests": ["karydia"], "radius": 10}}]}